[{"schemeId":74,"schemeName":"Incident","adapterType":"ivanti-heat-ua","group":null,"active":true,"adapterMetadataList":[],"requestHeaders":[],"restTemplates":{"UPDATE_RECORD":{"templateId":333,"operation":"UPDATE_RECORD","httpVerb":"PUT","restUrl":"api/odata/businessobject/${business object}('${recordId}')","specifications":{"Response":{"specId":639,"type":"Response","adapterType":null,"specType":"JOLT","status":"Active","specification":"[\n  {\n    \"operation\": \"shift\",\n    \"spec\": {\n      \"RecId\": \"id\",\n      \"*\": \"fields.&\"\n    }\n  },\n\n  {\n    \"operation\": \"modify-overwrite-beta\",\n    \"spec\": {\n      \"id\": \"=toString\"\n    }\n  },\n  {\n    \"operation\": \"shift\",\n    \"spec\": {\n      \"id\": \"&\",\n      \"fields\": \"&\"\n    }\n  }\n ]\n","samplePayload":"{\n  \"@odata.context\": \"https://connectall.trysaasit.com/api/odata/$metadata#incidents/$entity\",\n  \"ActualCategory_Valid\": \"6C23103F9BFD4906801FE833AEF17CBB\",\n  \"ActualCategory\": \"How-To\",\n  \"Category_Valid\": \"6C23103F9BFD4906801FE833AEF17CBB\",\n  \"Category\": \"How-To\",\n  \"CauseCode_Valid\": null,\n  \"CauseCode\": null,\n  \"ClosedBy\": null,\n  \"ClosedDateTime\": null,\n  \"ClosedDuration\": null,\n  \"CreatedBy\": \"Admin\",\n  \"CreatedDateTime\": \"2022-12-23T05:28:40Z\",\n  \"Email\": \"admin@saasitdemo.com\",\n  \"FirstCallResolution\": false,\n  \"Impact_Valid\": null,\n  \"Impact\": null,\n  \"IncidentNumber\": 12213,\n  \"IsNotification\": true,\n  \"IsVIP\": false,\n  \"IsWorkAround\": false,\n  \"LastModBy\": \"Admin\",\n  \"LastModDateTime\": \"2022-12-23T06:16:44Z\",\n  \"Phone\": \"7195551254\",\n  \"Priority_Valid\": \"29CD5D78E16F4D82916C3E933A600096\",\n  \"Priority\": \"3\",\n  \"ProfileFullName\": \"Administrator Admin\",\n  \"ProfileLink_Category\": \"Employee\",\n  \"ProfileLink_RecID\": \"FB884D18F7B746A0992880F2DFFE749C\",\n  \"ProfileLink\": \"FB884D18F7B746A0992880F2DFFE749C\",\n  \"RecId\": \"1D5D87ED63564839B1D656AA5B0A7C4C\",\n  \"Resolution\": null,\n  \"Service_Valid\": \"A912E98E55844765934A787FF3586F34\",\n  \"Service\": \"Service Desk\",\n  \"SLA\": \"\",\n  \"SLALink_Category\": null,\n  \"SLALink_RecID\": null,\n  \"SLALink\": null,\n  \"Source_Valid\": \"EF789CE160E742F99623DBB4D29C045C\",\n  \"Source\": \"Phone\",\n  \"Status_Valid\": \"EAB221009EE34AB4BC1D14A42ED099AA\",\n  \"Status\": \"Active\",\n  \"Subject\": \"Updated 3rd test from postman\",\n  \"Symptom\": \"Updated 3rd test\",\n  \"Urgency_Valid\": null,\n  \"Urgency\": null,\n  \"LoginId\": \"Admin\",\n  \"Owner_Valid\": \"FB884D18F7B746A0992880F2DFFE749C\",\n  \"Owner\": \"Admin\",\n  \"OwnerTeam_Valid\": \"2E4BABD54FB9420D94F836F0D9B80C47\",\n  \"OwnerTeam\": \"Service Desk\",\n  \"OwnerType\": \"Employee\",\n  \"IsNewRecord\": false,\n  \"AlternateContactLink_Category\": null,\n  \"AlternateContactLink_RecID\": null,\n  \"AlternateContactLink\": null,\n  \"ResolvedDateTime\": null,\n  \"ResolvedBy\": null,\n  \"HoursOfOperation_Valid\": \"FF57246B2E0047D193C1AEC1011D746B\",\n  \"HoursOfOperation\": \"Weekly HOP\",\n  \"OwnerEmail\": \"admin@saasitdemo.com\",\n  \"OwnerTeamEmail\": \"change@example.com\",\n  \"OwnershipAssignmentEmail\": \"change@example.com\",\n  \"CustomerLocation_Valid\": \"45199627E18542038C2818E49E68C32D\",\n  \"CustomerLocation\": \"USA\",\n  \"IsReportedByAlternateContact\": false,\n  \"ResolutionEscLink_Category\": \"Frs_data_escalation_watch\",\n  \"ResolutionEscLink_RecID\": \"D72A32ED98CB4D2A837D544AFE92EE97\",\n  \"ResolutionEscLink\": \"D72A32ED98CB4D2A837D544AFE92EE97\",\n  \"ResponseEscLink_Category\": \"Frs_data_escalation_watch\",\n  \"ResponseEscLink_RecID\": \"AACBCFAD2EC640748DCB3CB8532400C3\",\n  \"ResponseEscLink\": \"AACBCFAD2EC640748DCB3CB8532400C3\",\n  \"WaitingEscLink_Category\": \"Frs_data_escalation_watch\",\n  \"WaitingEscLink_RecID\": \"48367431B54B4CCAA664989C8C13A677\",\n  \"WaitingEscLink\": \"48367431B54B4CCAA664989C8C13A677\",\n  \"ClosingEscLink_Category\": \"Frs_data_escalation_watch\",\n  \"ClosingEscLink_RecID\": \"E90C58783948466ABD45513CFA768C9E\",\n  \"ClosingEscLink\": \"E90C58783948466ABD45513CFA768C9E\",\n  \"AlternateContactEmail\": null,\n  \"OrganizationUnitID\": \"GMI\",\n  \"ReportingOrgUnitID_Valid\": \"4A05123D660F408997A4FEE714DAD111\",\n  \"ReportingOrgUnitID\": \"GMI\",\n  \"TypeOfIncident\": \"Failure\",\n  \"AlternateContactPhone\": null,\n  \"TeamManagerEmail\": \"change@example.com\",\n  \"ProblemLink_Category\": null,\n  \"ProblemLink_RecID\": null,\n  \"ProblemLink\": null,\n  \"CustomerDepartment\": \"Corporate IT\",\n  \"ActualService_Valid\": \"A912E98E55844765934A787FF3586F34\",\n  \"ActualService\": \"Service Desk\",\n  \"CostPerMinute_Currency\": \"USD\",\n  \"CostPerMinute_CurrencyValid\": null,\n  \"CostPerMinute\": \"0.4000\",\n  \"IsInFinalState\": false,\n  \"IsReclassifiedForResolution\": false,\n  \"KnowledgeLink_Category\": null,\n  \"KnowledgeLink_RecID\": null,\n  \"KnowledgeLink\": null,\n  \"PreviousState\": null,\n  \"ResolvedByIncidentNumber\": null,\n  \"TotalTimeSpent\": null,\n  \"RespondedBy\": null,\n  \"RespondedDateTime\": null,\n  \"OrgUnitLink_Category\": \"OrganizationalUnit\",\n  \"OrgUnitLink_RecID\": \"4A05123D660F408997A4FEE714DAD111\",\n  \"OrgUnitLink\": \"4A05123D660F408997A4FEE714DAD111\",\n  \"OwningOrgUnitId_Valid\": \"4A05123D660F408997A4FEE714DAD111\",\n  \"OwningOrgUnitId\": \"GMI\",\n  \"ProgressBarPosition\": \"3\",\n  \"ResolvedByType\": null,\n  \"ReportedBy\": null,\n  \"NewNotes\": null,\n  \"CreatedByType\": \"Web Client\",\n  \"SLADisplayText\": \"\",\n  \"ServiceReqLink_Category\": null,\n  \"ServiceReqLink_RecID\": null,\n  \"ServiceReqLink\": null,\n  \"ReadOnly\": false,\n  \"Cost_Currency\": \"USD\",\n  \"Cost_CurrencyValid\": null,\n  \"Cost\": \"0.0000\",\n  \"IncidentDetailWorkflowTag\": null,\n  \"IncidentDetailSummary\": null,\n  \"IsApprovalNeeded\": false,\n  \"Approver_Valid\": \"D712FED92D154257AB053F8BF4D24015\",\n  \"Approver\": \"DemoHR.user@ivanticlouddev.com\",\n  \"IsDSMTaskExisted\": false,\n  \"ApprovalStatus\": null,\n  \"SocialTextHeader\": \"Incident 12213: Updated 3rd test from postman\",\n  \"Subcategory_Valid\": null,\n  \"Subcategory\": null,\n  \"helpdesk_Priority_Valid\": null,\n  \"helpdesk_Priority\": null,\n  \"ViewType\": null,\n  \"IncidentNetworkUserName\": \"Admin\",\n  \"SendSurveyNotification\": false,\n  \"EntityLink_Category\": \"OrganizationalUnit\",\n  \"EntityLink_RecID\": \"4A05123D660F408997A4FEE714DAD111\",\n  \"EntityLink\": \"4A05123D660F408997A4FEE714DAD111\",\n  \"EventCIRecId\": null,\n  \"IsMasterIncident\": false,\n  \"IsResolvedByMaster\": false,\n  \"MasterIncidentLink_Category\": null,\n  \"MasterIncidentLink_RecID\": null,\n  \"MasterIncidentLink\": null,\n  \"ServiceOwnerEmail\": \"admin@saasitdemo.com\",\n  \"IsRelatedIncidentUpdate\": false,\n  \"IsRelatedIncidentResolutionUpdate\": false,\n  \"IsUnRead\": false,\n  \"HRCaseLink_Category\": null,\n  \"HRCaseLink_RecID\": null,\n  \"HRCaseLink\": null,\n  \"ivnt_RequestforInformationorData\": false,\n  \"ivnt_UpdateRFI\": \"Chat Incident(s)\",\n  \"AddChatconversationtoActivityHistory\": false,\n  \"ivnt_TeamsUserDetailsLink_Category\": null,\n  \"ivnt_TeamsUserDetailsLink_RecID\": null,\n  \"ivnt_TeamsUserDetailsLink\": null,\n  \"VirimaAssetID\": null,\n  \"RecommendedCategory\": \"\",\n  \"RecommendedService\": \"\",\n  \"RecommendedSubCategory\": \"\",\n  \"Accuracy\": null,\n  \"IsRecommended\": false,\n  \"RecomService\": null,\n  \"RecomCategory\": null,\n  \"RecomSubCategory\": null,\n  \"IsRunTicketClassification\": true\n}","contentAvailable":true,"statusCode":2},"Request":{"specId":640,"type":"Request","adapterType":null,"specType":"JOLT","status":"Active","specification":"[\n  {\n    \"operation\": \"remove\",\n    \"spec\": {\n      \"id\": \"\",\n      \"fields\": {\n        \"business object\": \"\",\n        \"id\": \"\"\n      }\n    }\n  },\n  {\n    \"operation\": \"shift\",\n    \"spec\": {\n      \"fields\": \"\"\n    }\n  }\n]\n","samplePayload":"{\n  \"id\": \"TP-4\",\n  \"fields\": {\n    \"summary\": \"Test for API creation 2\",\n    \"description\": \"Test for API creation 2\",\n    \"assignee\": \"admin\",\n    \"priority\": \"1\",\n    \"reporter\": \"admin\"\n  }\n}","contentAvailable":true,"statusCode":2}}},"QUERY_RECORD_BY_ID":{"templateId":331,"operation":"QUERY_RECORD_BY_ID","httpVerb":"GET","restUrl":"api/odata/businessobject/${business object}('${recordId}')","specifications":{"Response":{"specId":635,"type":"Response","adapterType":null,"specType":"JOLT","status":"Active","specification":"[\n  {\n    \"operation\": \"shift\",\n    \"spec\": {\n      \"RecId\": \"id\",\n      \"*\": \"fields.&\"\n    }\n  },\n  {\n    \"operation\": \"modify-overwrite-beta\",\n    \"spec\": {\n      \"id\": \"=toString\"\n    }\n  },\n  {\n    \"operation\": \"shift\",\n    \"spec\": {\n      \"id\": \"&\",\n      \"fields\": \"&\"\n    }\n  }\n ]\n","samplePayload":"{\n  \"@odata.context\": \"https://connectall.trysaasit.com/api/odata/$metadata#incidents/$entity\",\n  \"ActualCategory_Valid\": \"6C23103F9BFD4906801FE833AEF17CBB\",\n  \"ActualCategory\": \"How-To\",\n  \"Category_Valid\": \"6C23103F9BFD4906801FE833AEF17CBB\",\n  \"Category\": \"How-To\",\n  \"CauseCode_Valid\": null,\n  \"CauseCode\": null,\n  \"ClosedBy\": null,\n  \"ClosedDateTime\": null,\n  \"ClosedDuration\": null,\n  \"CreatedBy\": \"Admin\",\n  \"CreatedDateTime\": \"2022-12-23T05:28:40Z\",\n  \"Email\": \"admin@saasitdemo.com\",\n  \"FirstCallResolution\": false,\n  \"Impact_Valid\": null,\n  \"Impact\": null,\n  \"IncidentNumber\": 12213,\n  \"IsNotification\": true,\n  \"IsVIP\": false,\n  \"IsWorkAround\": false,\n  \"LastModBy\": \"InternalServices\",\n  \"LastModDateTime\": \"2022-12-23T05:28:42Z\",\n  \"Phone\": \"7195551254\",\n  \"Priority_Valid\": \"29CD5D78E16F4D82916C3E933A600096\",\n  \"Priority\": \"3\",\n  \"ProfileFullName\": \"Administrator Admin\",\n  \"ProfileLink_Category\": \"Employee\",\n  \"ProfileLink_RecID\": \"FB884D18F7B746A0992880F2DFFE749C\",\n  \"ProfileLink\": \"FB884D18F7B746A0992880F2DFFE749C\",\n  \"RecId\": \"1D5D87ED63564839B1D656AA5B0A7C4C\",\n  \"Resolution\": null,\n  \"Service_Valid\": \"A912E98E55844765934A787FF3586F34\",\n  \"Service\": \"Service Desk\",\n  \"SLA\": \"\",\n  \"SLALink_Category\": null,\n  \"SLALink_RecID\": null,\n  \"SLALink\": null,\n  \"Source_Valid\": \"EF789CE160E742F99623DBB4D29C045C\",\n  \"Source\": \"Phone\",\n  \"Status_Valid\": \"EAB221009EE34AB4BC1D14A42ED099AA\",\n  \"Status\": \"Active\",\n  \"Subject\": \"3rd test from postman\",\n  \"Symptom\": \"3rd test\",\n  \"Urgency_Valid\": null,\n  \"Urgency\": null,\n  \"LoginId\": \"Admin\",\n  \"Owner_Valid\": \"FB884D18F7B746A0992880F2DFFE749C\",\n  \"Owner\": \"Admin\",\n  \"OwnerTeam_Valid\": \"2E4BABD54FB9420D94F836F0D9B80C47\",\n  \"OwnerTeam\": \"Service Desk\",\n  \"OwnerType\": \"Employee\",\n  \"IsNewRecord\": false,\n  \"AlternateContactLink_Category\": null,\n  \"AlternateContactLink_RecID\": null,\n  \"AlternateContactLink\": null,\n  \"ResolvedDateTime\": null,\n  \"ResolvedBy\": null,\n  \"HoursOfOperation_Valid\": \"FF57246B2E0047D193C1AEC1011D746B\",\n  \"HoursOfOperation\": \"Weekly HOP\",\n  \"OwnerEmail\": \"admin@saasitdemo.com\",\n  \"OwnerTeamEmail\": \"change@example.com\",\n  \"OwnershipAssignmentEmail\": \"change@example.com\",\n  \"CustomerLocation_Valid\": \"45199627E18542038C2818E49E68C32D\",\n  \"CustomerLocation\": \"USA\",\n  \"IsReportedByAlternateContact\": false,\n  \"ResolutionEscLink_Category\": \"Frs_data_escalation_watch\",\n  \"ResolutionEscLink_RecID\": \"D72A32ED98CB4D2A837D544AFE92EE97\",\n  \"ResolutionEscLink\": \"D72A32ED98CB4D2A837D544AFE92EE97\",\n  \"ResponseEscLink_Category\": \"Frs_data_escalation_watch\",\n  \"ResponseEscLink_RecID\": \"AACBCFAD2EC640748DCB3CB8532400C3\",\n  \"ResponseEscLink\": \"AACBCFAD2EC640748DCB3CB8532400C3\",\n  \"WaitingEscLink_Category\": \"Frs_data_escalation_watch\",\n  \"WaitingEscLink_RecID\": \"48367431B54B4CCAA664989C8C13A677\",\n  \"WaitingEscLink\": \"48367431B54B4CCAA664989C8C13A677\",\n  \"ClosingEscLink_Category\": \"Frs_data_escalation_watch\",\n  \"ClosingEscLink_RecID\": \"E90C58783948466ABD45513CFA768C9E\",\n  \"ClosingEscLink\": \"E90C58783948466ABD45513CFA768C9E\",\n  \"AlternateContactEmail\": null,\n  \"OrganizationUnitID\": \"GMI\",\n  \"ReportingOrgUnitID_Valid\": \"4A05123D660F408997A4FEE714DAD111\",\n  \"ReportingOrgUnitID\": \"GMI\",\n  \"TypeOfIncident\": \"Failure\",\n  \"AlternateContactPhone\": null,\n  \"TeamManagerEmail\": \"change@example.com\",\n  \"ProblemLink_Category\": null,\n  \"ProblemLink_RecID\": null,\n  \"ProblemLink\": null,\n  \"CustomerDepartment\": \"Corporate IT\",\n  \"ActualService_Valid\": \"A912E98E55844765934A787FF3586F34\",\n  \"ActualService\": \"Service Desk\",\n  \"CostPerMinute_Currency\": \"USD\",\n  \"CostPerMinute_CurrencyValid\": null,\n  \"CostPerMinute\": \"0.4000\",\n  \"IsInFinalState\": false,\n  \"IsReclassifiedForResolution\": false,\n  \"KnowledgeLink_Category\": null,\n  \"KnowledgeLink_RecID\": null,\n  \"KnowledgeLink\": null,\n  \"PreviousState\": null,\n  \"ResolvedByIncidentNumber\": null,\n  \"TotalTimeSpent\": null,\n  \"RespondedBy\": null,\n  \"RespondedDateTime\": null,\n  \"OrgUnitLink_Category\": \"OrganizationalUnit\",\n  \"OrgUnitLink_RecID\": \"4A05123D660F408997A4FEE714DAD111\",\n  \"OrgUnitLink\": \"4A05123D660F408997A4FEE714DAD111\",\n  \"OwningOrgUnitId_Valid\": \"4A05123D660F408997A4FEE714DAD111\",\n  \"OwningOrgUnitId\": \"GMI\",\n  \"ProgressBarPosition\": \"3\",\n  \"ResolvedByType\": null,\n  \"ReportedBy\": null,\n  \"NewNotes\": null,\n  \"CreatedByType\": \"Web Client\",\n  \"SLADisplayText\": \"\",\n  \"ServiceReqLink_Category\": null,\n  \"ServiceReqLink_RecID\": null,\n  \"ServiceReqLink\": null,\n  \"ReadOnly\": false,\n  \"Cost_Currency\": \"USD\",\n  \"Cost_CurrencyValid\": null,\n  \"Cost\": \"0.0000\",\n  \"IncidentDetailWorkflowTag\": null,\n  \"IncidentDetailSummary\": null,\n  \"IsApprovalNeeded\": false,\n  \"Approver_Valid\": \"D712FED92D154257AB053F8BF4D24015\",\n  \"Approver\": \"DemoHR.user@ivanticlouddev.com\",\n  \"IsDSMTaskExisted\": false,\n  \"ApprovalStatus\": null,\n  \"SocialTextHeader\": \"Incident 12213: 3rd test from postman\",\n  \"Subcategory_Valid\": null,\n  \"Subcategory\": null,\n  \"helpdesk_Priority_Valid\": null,\n  \"helpdesk_Priority\": null,\n  \"ViewType\": null,\n  \"IncidentNetworkUserName\": \"Admin\",\n  \"SendSurveyNotification\": false,\n  \"EntityLink_Category\": \"OrganizationalUnit\",\n  \"EntityLink_RecID\": \"4A05123D660F408997A4FEE714DAD111\",\n  \"EntityLink\": \"4A05123D660F408997A4FEE714DAD111\",\n  \"EventCIRecId\": null,\n  \"IsMasterIncident\": false,\n  \"IsResolvedByMaster\": false,\n  \"MasterIncidentLink_Category\": null,\n  \"MasterIncidentLink_RecID\": null,\n  \"MasterIncidentLink\": null,\n  \"ServiceOwnerEmail\": \"admin@saasitdemo.com\",\n  \"IsRelatedIncidentUpdate\": false,\n  \"IsRelatedIncidentResolutionUpdate\": false,\n  \"IsUnRead\": false,\n  \"HRCaseLink_Category\": null,\n  \"HRCaseLink_RecID\": null,\n  \"HRCaseLink\": null,\n  \"ivnt_RequestforInformationorData\": false,\n  \"ivnt_UpdateRFI\": \"Chat Incident(s)\",\n  \"AddChatconversationtoActivityHistory\": false,\n  \"ivnt_TeamsUserDetailsLink_Category\": null,\n  \"ivnt_TeamsUserDetailsLink_RecID\": null,\n  \"ivnt_TeamsUserDetailsLink\": null,\n  \"VirimaAssetID\": null,\n  \"RecommendedCategory\": null,\n  \"RecommendedService\": null,\n  \"RecommendedSubCategory\": null,\n  \"Accuracy\": null,\n  \"IsRecommended\": false,\n  \"RecomService\": null,\n  \"RecomCategory\": null,\n  \"RecomSubCategory\": null,\n  \"IsRunTicketClassification\": true\n}","contentAvailable":true,"statusCode":2},"Request":{"specId":636,"type":"Request","adapterType":null,"specType":null,"status":"Active","specification":null,"samplePayload":null,"contentAvailable":false,"statusCode":2}}},"CREATE_RECORD":{"templateId":332,"operation":"CREATE_RECORD","httpVerb":"POST","restUrl":"api/odata/businessobject/${business object}","specifications":{"Response":{"specId":637,"type":"Response","adapterType":null,"specType":"JOLT","status":"Active","specification":"[\n  {\n    \"operation\": \"shift\",\n    \"spec\": {\n      \"RecId\": \"id\",\n      \"*\": \"fields.&\"\n    }\n  },\n  {\n    \"operation\": \"modify-overwrite-beta\",\n    \"spec\": {\n      \"id\": \"=toString\"\n    }\n  },\n  {\n    \"operation\": \"shift\",\n    \"spec\": {\n      \"id\": \"&\",\n      \"fields\": \"&\"\n    }\n  }\n ]\n","samplePayload":"{\n  \"@odata.context\": \"https://connectall.trysaasit.com/api/odata/$metadata#incidents/$entity\",\n  \"ActualCategory_Valid\": \"6C23103F9BFD4906801FE833AEF17CBB\",\n  \"ActualCategory\": \"How-To\",\n  \"Category_Valid\": \"6C23103F9BFD4906801FE833AEF17CBB\",\n  \"Category\": \"How-To\",\n  \"CauseCode_Valid\": null,\n  \"CauseCode\": null,\n  \"ClosedBy\": null,\n  \"ClosedDateTime\": null,\n  \"ClosedDuration\": null,\n  \"CreatedBy\": \"Admin\",\n  \"CreatedDateTime\": \"2022-12-23T05:28:40Z\",\n  \"Email\": \"admin@saasitdemo.com\",\n  \"FirstCallResolution\": false,\n  \"Impact_Valid\": null,\n  \"Impact\": null,\n  \"IncidentNumber\": 12213,\n  \"IsNotification\": true,\n  \"IsVIP\": false,\n  \"IsWorkAround\": false,\n  \"LastModBy\": \"Admin\",\n  \"LastModDateTime\": \"2022-12-23T05:28:41Z\",\n  \"Phone\": \"7195551254\",\n  \"Priority_Valid\": \"29CD5D78E16F4D82916C3E933A600096\",\n  \"Priority\": \"3\",\n  \"ProfileFullName\": \"Administrator Admin\",\n  \"ProfileLink_Category\": \"Employee\",\n  \"ProfileLink_RecID\": \"FB884D18F7B746A0992880F2DFFE749C\",\n  \"ProfileLink\": \"FB884D18F7B746A0992880F2DFFE749C\",\n  \"RecId\": \"1D5D87ED63564839B1D656AA5B0A7C4C\",\n  \"Resolution\": null,\n  \"Service_Valid\": \"A912E98E55844765934A787FF3586F34\",\n  \"Service\": \"Service Desk\",\n  \"SLA\": \"\",\n  \"SLALink_Category\": null,\n  \"SLALink_RecID\": null,\n  \"SLALink\": null,\n  \"Source_Valid\": \"EF789CE160E742F99623DBB4D29C045C\",\n  \"Source\": \"Phone\",\n  \"Status_Valid\": \"EAB221009EE34AB4BC1D14A42ED099AA\",\n  \"Status\": \"Active\",\n  \"Subject\": \"3rd test from postman\",\n  \"Symptom\": \"3rd test\",\n  \"Urgency_Valid\": null,\n  \"Urgency\": null,\n  \"LoginId\": \"Admin\",\n  \"Owner_Valid\": \"FB884D18F7B746A0992880F2DFFE749C\",\n  \"Owner\": \"Admin\",\n  \"OwnerTeam_Valid\": \"2E4BABD54FB9420D94F836F0D9B80C47\",\n  \"OwnerTeam\": \"Service Desk\",\n  \"OwnerType\": \"Employee\",\n  \"IsNewRecord\": false,\n  \"AlternateContactLink_Category\": null,\n  \"AlternateContactLink_RecID\": null,\n  \"AlternateContactLink\": null,\n  \"ResolvedDateTime\": null,\n  \"ResolvedBy\": null,\n  \"HoursOfOperation_Valid\": \"FF57246B2E0047D193C1AEC1011D746B\",\n  \"HoursOfOperation\": \"Weekly HOP\",\n  \"OwnerEmail\": \"admin@saasitdemo.com\",\n  \"OwnerTeamEmail\": \"change@example.com\",\n  \"OwnershipAssignmentEmail\": \"change@example.com\",\n  \"CustomerLocation_Valid\": \"45199627E18542038C2818E49E68C32D\",\n  \"CustomerLocation\": \"USA\",\n  \"IsReportedByAlternateContact\": false,\n  \"ResolutionEscLink_Category\": null,\n  \"ResolutionEscLink_RecID\": null,\n  \"ResolutionEscLink\": null,\n  \"ResponseEscLink_Category\": null,\n  \"ResponseEscLink_RecID\": null,\n  \"ResponseEscLink\": null,\n  \"WaitingEscLink_Category\": null,\n  \"WaitingEscLink_RecID\": null,\n  \"WaitingEscLink\": null,\n  \"ClosingEscLink_Category\": null,\n  \"ClosingEscLink_RecID\": null,\n  \"ClosingEscLink\": null,\n  \"AlternateContactEmail\": null,\n  \"OrganizationUnitID\": \"GMI\",\n  \"ReportingOrgUnitID_Valid\": \"4A05123D660F408997A4FEE714DAD111\",\n  \"ReportingOrgUnitID\": \"GMI\",\n  \"TypeOfIncident\": \"Failure\",\n  \"AlternateContactPhone\": null,\n  \"TeamManagerEmail\": \"change@example.com\",\n  \"ProblemLink_Category\": null,\n  \"ProblemLink_RecID\": null,\n  \"ProblemLink\": null,\n  \"CustomerDepartment\": \"Corporate IT\",\n  \"ActualService_Valid\": \"A912E98E55844765934A787FF3586F34\",\n  \"ActualService\": \"Service Desk\",\n  \"CostPerMinute_Currency\": \"USD\",\n  \"CostPerMinute_CurrencyValid\": null,\n  \"CostPerMinute\": \"0.4000\",\n  \"IsInFinalState\": false,\n  \"IsReclassifiedForResolution\": false,\n  \"KnowledgeLink_Category\": null,\n  \"KnowledgeLink_RecID\": null,\n  \"KnowledgeLink\": null,\n  \"PreviousState\": null,\n  \"ResolvedByIncidentNumber\": null,\n  \"TotalTimeSpent\": null,\n  \"RespondedBy\": null,\n  \"RespondedDateTime\": null,\n  \"OrgUnitLink_Category\": \"OrganizationalUnit\",\n  \"OrgUnitLink_RecID\": \"4A05123D660F408997A4FEE714DAD111\",\n  \"OrgUnitLink\": \"4A05123D660F408997A4FEE714DAD111\",\n  \"OwningOrgUnitId_Valid\": \"4A05123D660F408997A4FEE714DAD111\",\n  \"OwningOrgUnitId\": \"GMI\",\n  \"ProgressBarPosition\": \"3\",\n  \"ResolvedByType\": null,\n  \"ReportedBy\": null,\n  \"NewNotes\": null,\n  \"CreatedByType\": \"Web Client\",\n  \"SLADisplayText\": \"\",\n  \"ServiceReqLink_Category\": null,\n  \"ServiceReqLink_RecID\": null,\n  \"ServiceReqLink\": null,\n  \"ReadOnly\": false,\n  \"Cost_Currency\": \"USD\",\n  \"Cost_CurrencyValid\": null,\n  \"Cost\": \"0.0000\",\n  \"IncidentDetailWorkflowTag\": null,\n  \"IncidentDetailSummary\": null,\n  \"IsApprovalNeeded\": false,\n  \"Approver_Valid\": \"D712FED92D154257AB053F8BF4D24015\",\n  \"Approver\": \"DemoHR.user@ivanticlouddev.com\",\n  \"IsDSMTaskExisted\": false,\n  \"ApprovalStatus\": null,\n  \"SocialTextHeader\": \"Incident 12213: 3rd test from postman\",\n  \"Subcategory_Valid\": null,\n  \"Subcategory\": null,\n  \"helpdesk_Priority_Valid\": null,\n  \"helpdesk_Priority\": null,\n  \"ViewType\": null,\n  \"IncidentNetworkUserName\": \"Admin\",\n  \"SendSurveyNotification\": false,\n  \"EntityLink_Category\": \"OrganizationalUnit\",\n  \"EntityLink_RecID\": \"4A05123D660F408997A4FEE714DAD111\",\n  \"EntityLink\": \"4A05123D660F408997A4FEE714DAD111\",\n  \"EventCIRecId\": null,\n  \"IsMasterIncident\": false,\n  \"IsResolvedByMaster\": false,\n  \"MasterIncidentLink_Category\": null,\n  \"MasterIncidentLink_RecID\": null,\n  \"MasterIncidentLink\": null,\n  \"ServiceOwnerEmail\": \"admin@saasitdemo.com\",\n  \"IsRelatedIncidentUpdate\": false,\n  \"IsRelatedIncidentResolutionUpdate\": false,\n  \"IsUnRead\": false,\n  \"HRCaseLink_Category\": null,\n  \"HRCaseLink_RecID\": null,\n  \"HRCaseLink\": null,\n  \"ivnt_RequestforInformationorData\": false,\n  \"ivnt_UpdateRFI\": \"Chat Incident(s)\",\n  \"AddChatconversationtoActivityHistory\": false,\n  \"ivnt_TeamsUserDetailsLink_Category\": null,\n  \"ivnt_TeamsUserDetailsLink_RecID\": null,\n  \"ivnt_TeamsUserDetailsLink\": null,\n  \"VirimaAssetID\": null,\n  \"RecommendedCategory\": null,\n  \"RecommendedService\": null,\n  \"RecommendedSubCategory\": null,\n  \"Accuracy\": null,\n  \"IsRecommended\": false,\n  \"RecomService\": null,\n  \"RecomCategory\": null,\n  \"RecomSubCategory\": null,\n  \"IsRunTicketClassification\": true\n}","contentAvailable":true,"statusCode":2},"Request":{"specId":638,"type":"Request","adapterType":null,"specType":"JOLT","status":"Active","specification":"[\n  {\n    \"operation\": \"remove\",\n    \"spec\": {\n      \"business object\": \"\"\n    }\n  },\n  {\n    \"operation\": \"shift\",\n    \"spec\": {\n      \"fields\": \"\"\n    }\n  }\n ]\n","samplePayload":"{\n  \"fields\": {\n    \"summary\": \"Test for API creation 2\",\n    \"description\": \"Test for API creation 2\",\n    \"priority\": \"1\",\n    \"modifiedTime\": \"01-04-2019 11:46:30.124\",\n    \"severity\": \"2\",\n    \"status\": \"Open\"\n  }\n}","contentAvailable":true,"statusCode":2}}},"QUERY_MODIFIED_RECORDS":{"templateId":330,"operation":"QUERY_MODIFIED_RECORDS","httpVerb":"GET","restUrl":"api/odata/businessobject/${business object}?$filter=LastModDateTime%20gt%20${last-modified-time}","specifications":{"Response":{"specId":633,"type":"Response","adapterType":null,"specType":"JOLT","status":"Active","specification":"[\n  {\n    \"operation\": \"shift\",\n    \"spec\": {\n      \"value\": {\n        \"*\": {\n          \"RecId\": \"result.[&1].id\",\n          \"*\": \"result.[&1].fields.&\"\n        }\n      }\n    }\n  },\n  {\n    \"operation\": \"modify-overwrite-beta\",\n    \"spec\": {\n      \"totalrecords\": \"=size(@(1,result))\",\n      \"result\": {\n        \"*\": {\n          \"id\": \"=toString\"\n        }\n      }\n    }\n  },\n  {\n    \"operation\": \"shift\",\n    \"spec\": {\n      \"totalrecords\": \"&\",\n      \"result\": {\n        \"*\": {\n          \"id\": \"result.[&1].&\",\n          \"fields\": \"result.[&1].&\"\n        }\n      }\n    }\n  }, {\n    \"operation\": \"default\",\n    \"spec\": {\n      \"totalrecords\": 0,\n      \"result\": []\n    }\n   }\n]\n","samplePayload":"{\n  \"@odata.context\": \"https://connectall.trysaasit.com/api/odata/$metadata#incidents\",\n  \"@odata.count\": 3,\n  \"value\": [\n    {\n      \"ActualCategory_Valid\": \"6C23103F9BFD4906801FE833AEF17CBB\",\n      \"ActualCategory\": \"How-To\",\n      \"Category_Valid\": \"6C23103F9BFD4906801FE833AEF17CBB\",\n      \"Category\": \"How-To\",\n      \"CauseCode_Valid\": null,\n      \"CauseCode\": null,\n      \"ClosedBy\": null,\n      \"ClosedDateTime\": null,\n      \"ClosedDuration\": null,\n      \"CreatedBy\": \"Admin\",\n      \"CreatedDateTime\": \"2022-12-23T05:28:40Z\",\n      \"Email\": \"admin@saasitdemo.com\",\n      \"FirstCallResolution\": false,\n      \"Impact_Valid\": null,\n      \"Impact\": null,\n      \"IncidentNumber\": 12213,\n      \"IsNotification\": true,\n      \"IsVIP\": false,\n      \"IsWorkAround\": false,\n      \"LastModBy\": \"InternalServices\",\n      \"LastModDateTime\": \"2022-12-23T05:28:42Z\",\n      \"Phone\": \"7195551254\",\n      \"Priority_Valid\": \"29CD5D78E16F4D82916C3E933A600096\",\n      \"Priority\": \"3\",\n      \"ProfileFullName\": \"Administrator Admin\",\n      \"ProfileLink_Category\": \"Employee\",\n      \"ProfileLink_RecID\": \"FB884D18F7B746A0992880F2DFFE749C\",\n      \"ProfileLink\": \"FB884D18F7B746A0992880F2DFFE749C\",\n      \"RecId\": \"1D5D87ED63564839B1D656AA5B0A7C4C\",\n      \"Resolution\": null,\n      \"Service_Valid\": \"A912E98E55844765934A787FF3586F34\",\n      \"Service\": \"Service Desk\",\n      \"SLA\": \"\",\n      \"SLALink_Category\": null,\n      \"SLALink_RecID\": null,\n      \"SLALink\": null,\n      \"Source_Valid\": \"EF789CE160E742F99623DBB4D29C045C\",\n      \"Source\": \"Phone\",\n      \"Status_Valid\": \"EAB221009EE34AB4BC1D14A42ED099AA\",\n      \"Status\": \"Active\",\n      \"Subject\": \"3rd test from postman\",\n      \"Symptom\": \"3rd test\",\n      \"Urgency_Valid\": null,\n      \"Urgency\": null,\n      \"LoginId\": \"Admin\",\n      \"Owner_Valid\": \"FB884D18F7B746A0992880F2DFFE749C\",\n      \"Owner\": \"Admin\",\n      \"OwnerTeam_Valid\": \"2E4BABD54FB9420D94F836F0D9B80C47\",\n      \"OwnerTeam\": \"Service Desk\",\n      \"OwnerType\": \"Employee\",\n      \"IsNewRecord\": false,\n      \"AlternateContactLink_Category\": null,\n      \"AlternateContactLink_RecID\": null,\n      \"AlternateContactLink\": null,\n      \"ResolvedDateTime\": null,\n      \"ResolvedBy\": null,\n      \"HoursOfOperation_Valid\": \"FF57246B2E0047D193C1AEC1011D746B\",\n      \"HoursOfOperation\": \"Weekly HOP\",\n      \"OwnerEmail\": \"admin@saasitdemo.com\",\n      \"OwnerTeamEmail\": \"change@example.com\",\n      \"OwnershipAssignmentEmail\": \"change@example.com\",\n      \"CustomerLocation_Valid\": \"45199627E18542038C2818E49E68C32D\",\n      \"CustomerLocation\": \"USA\",\n      \"IsReportedByAlternateContact\": false,\n      \"ResolutionEscLink_Category\": \"Frs_data_escalation_watch\",\n      \"ResolutionEscLink_RecID\": \"D72A32ED98CB4D2A837D544AFE92EE97\",\n      \"ResolutionEscLink\": \"D72A32ED98CB4D2A837D544AFE92EE97\",\n      \"ResponseEscLink_Category\": \"Frs_data_escalation_watch\",\n      \"ResponseEscLink_RecID\": \"AACBCFAD2EC640748DCB3CB8532400C3\",\n      \"ResponseEscLink\": \"AACBCFAD2EC640748DCB3CB8532400C3\",\n      \"WaitingEscLink_Category\": \"Frs_data_escalation_watch\",\n      \"WaitingEscLink_RecID\": \"48367431B54B4CCAA664989C8C13A677\",\n      \"WaitingEscLink\": \"48367431B54B4CCAA664989C8C13A677\",\n      \"ClosingEscLink_Category\": \"Frs_data_escalation_watch\",\n      \"ClosingEscLink_RecID\": \"E90C58783948466ABD45513CFA768C9E\",\n      \"ClosingEscLink\": \"E90C58783948466ABD45513CFA768C9E\",\n      \"AlternateContactEmail\": null,\n      \"OrganizationUnitID\": \"GMI\",\n      \"ReportingOrgUnitID_Valid\": \"4A05123D660F408997A4FEE714DAD111\",\n      \"ReportingOrgUnitID\": \"GMI\",\n      \"TypeOfIncident\": \"Failure\",\n      \"AlternateContactPhone\": null,\n      \"TeamManagerEmail\": \"change@example.com\",\n      \"ProblemLink_Category\": null,\n      \"ProblemLink_RecID\": null,\n      \"ProblemLink\": null,\n      \"CustomerDepartment\": \"Corporate IT\",\n      \"ActualService_Valid\": \"A912E98E55844765934A787FF3586F34\",\n      \"ActualService\": \"Service Desk\",\n      \"CostPerMinute_Currency\": \"USD\",\n      \"CostPerMinute_CurrencyValid\": null,\n      \"CostPerMinute\": \"0.4000\",\n      \"IsInFinalState\": false,\n      \"IsReclassifiedForResolution\": false,\n      \"KnowledgeLink_Category\": null,\n      \"KnowledgeLink_RecID\": null,\n      \"KnowledgeLink\": null,\n      \"PreviousState\": null,\n      \"ResolvedByIncidentNumber\": null,\n      \"TotalTimeSpent\": null,\n      \"RespondedBy\": null,\n      \"RespondedDateTime\": null,\n      \"OrgUnitLink_Category\": \"OrganizationalUnit\",\n      \"OrgUnitLink_RecID\": \"4A05123D660F408997A4FEE714DAD111\",\n      \"OrgUnitLink\": \"4A05123D660F408997A4FEE714DAD111\",\n      \"OwningOrgUnitId_Valid\": \"4A05123D660F408997A4FEE714DAD111\",\n      \"OwningOrgUnitId\": \"GMI\",\n      \"ProgressBarPosition\": \"3\",\n      \"ResolvedByType\": null,\n      \"ReportedBy\": null,\n      \"NewNotes\": null,\n      \"CreatedByType\": \"Web Client\",\n      \"SLADisplayText\": \"\",\n      \"ServiceReqLink_Category\": null,\n      \"ServiceReqLink_RecID\": null,\n      \"ServiceReqLink\": null,\n      \"ReadOnly\": false,\n      \"Cost_Currency\": \"USD\",\n      \"Cost_CurrencyValid\": null,\n      \"Cost\": \"0.0000\",\n      \"IncidentDetailWorkflowTag\": null,\n      \"IncidentDetailSummary\": null,\n      \"IsApprovalNeeded\": false,\n      \"Approver_Valid\": \"D712FED92D154257AB053F8BF4D24015\",\n      \"Approver\": \"DemoHR.user@ivanticlouddev.com\",\n      \"IsDSMTaskExisted\": false,\n      \"ApprovalStatus\": null,\n      \"SocialTextHeader\": \"Incident 12213: 3rd test from postman\",\n      \"Subcategory_Valid\": null,\n      \"Subcategory\": null,\n      \"helpdesk_Priority_Valid\": null,\n      \"helpdesk_Priority\": null,\n      \"ViewType\": null,\n      \"IncidentNetworkUserName\": \"Admin\",\n      \"SendSurveyNotification\": false,\n      \"EntityLink_Category\": \"OrganizationalUnit\",\n      \"EntityLink_RecID\": \"4A05123D660F408997A4FEE714DAD111\",\n      \"EntityLink\": \"4A05123D660F408997A4FEE714DAD111\",\n      \"EventCIRecId\": null,\n      \"IsMasterIncident\": false,\n      \"IsResolvedByMaster\": false,\n      \"MasterIncidentLink_Category\": null,\n      \"MasterIncidentLink_RecID\": null,\n      \"MasterIncidentLink\": null,\n      \"ServiceOwnerEmail\": \"admin@saasitdemo.com\",\n      \"IsRelatedIncidentUpdate\": false,\n      \"IsRelatedIncidentResolutionUpdate\": false,\n      \"IsUnRead\": false,\n      \"HRCaseLink_Category\": null,\n      \"HRCaseLink_RecID\": null,\n      \"HRCaseLink\": null,\n      \"ivnt_RequestforInformationorData\": false,\n      \"ivnt_UpdateRFI\": \"Chat Incident(s)\",\n      \"AddChatconversationtoActivityHistory\": false,\n      \"ivnt_TeamsUserDetailsLink_Category\": null,\n      \"ivnt_TeamsUserDetailsLink_RecID\": null,\n      \"ivnt_TeamsUserDetailsLink\": null,\n      \"VirimaAssetID\": null,\n      \"RecommendedCategory\": null,\n      \"RecommendedService\": null,\n      \"RecommendedSubCategory\": null,\n      \"Accuracy\": null,\n      \"IsRecommended\": false,\n      \"RecomService\": null,\n      \"RecomCategory\": null,\n      \"RecomSubCategory\": null,\n      \"IsRunTicketClassification\": true\n    },\n    {\n      \"ActualCategory_Valid\": \"601387668EAE4F09BB6D8DE4E922B2C7\",\n      \"ActualCategory\": \"Connectivity\",\n      \"Category_Valid\": \"601387668EAE4F09BB6D8DE4E922B2C7\",\n      \"Category\": \"Connectivity\",\n      \"CauseCode_Valid\": null,\n      \"CauseCode\": null,\n      \"ClosedBy\": null,\n      \"ClosedDateTime\": null,\n      \"ClosedDuration\": null,\n      \"CreatedBy\": \"Admin\",\n      \"CreatedDateTime\": \"2022-12-23T05:20:10Z\",\n      \"Email\": \"admin@saasitdemo.com\",\n      \"FirstCallResolution\": false,\n      \"Impact_Valid\": null,\n      \"Impact\": null,\n      \"IncidentNumber\": 12211,\n      \"IsNotification\": true,\n      \"IsVIP\": false,\n      \"IsWorkAround\": false,\n      \"LastModBy\": \"InternalServices\",\n      \"LastModDateTime\": \"2022-12-23T05:20:12Z\",\n      \"Phone\": \"7195551254\",\n      \"Priority_Valid\": \"29CD5D78E16F4D82916C3E933A600096\",\n      \"Priority\": \"3\",\n      \"ProfileFullName\": \"Administrator Admin\",\n      \"ProfileLink_Category\": \"Employee\",\n      \"ProfileLink_RecID\": \"FB884D18F7B746A0992880F2DFFE749C\",\n      \"ProfileLink\": \"FB884D18F7B746A0992880F2DFFE749C\",\n      \"RecId\": \"60FFE5762E7149BE923511268897D995\",\n      \"Resolution\": null,\n      \"Service_Valid\": \"A912E98E55844765934A787FF3586F34\",\n      \"Service\": \"Service Desk\",\n      \"SLA\": \"\",\n      \"SLALink_Category\": null,\n      \"SLALink_RecID\": null,\n      \"SLALink\": null,\n      \"Source_Valid\": \"EF789CE160E742F99623DBB4D29C045C\",\n      \"Source\": \"Phone\",\n      \"Status_Valid\": \"EAB221009EE34AB4BC1D14A42ED099AA\",\n      \"Status\": \"Active\",\n      \"Subject\": \"2nd test from postman\",\n      \"Symptom\": \"2nd test\",\n      \"Urgency_Valid\": null,\n      \"Urgency\": null,\n      \"LoginId\": \"Admin\",\n      \"Owner_Valid\": \"FB884D18F7B746A0992880F2DFFE749C\",\n      \"Owner\": \"Admin\",\n      \"OwnerTeam_Valid\": \"2E4BABD54FB9420D94F836F0D9B80C47\",\n      \"OwnerTeam\": \"Service Desk\",\n      \"OwnerType\": \"Employee\",\n      \"IsNewRecord\": false,\n      \"AlternateContactLink_Category\": null,\n      \"AlternateContactLink_RecID\": null,\n      \"AlternateContactLink\": null,\n      \"ResolvedDateTime\": null,\n      \"ResolvedBy\": null,\n      \"HoursOfOperation_Valid\": \"FF57246B2E0047D193C1AEC1011D746B\",\n      \"HoursOfOperation\": \"Weekly HOP\",\n      \"OwnerEmail\": \"admin@saasitdemo.com\",\n      \"OwnerTeamEmail\": \"change@example.com\",\n      \"OwnershipAssignmentEmail\": \"change@example.com\",\n      \"CustomerLocation_Valid\": \"45199627E18542038C2818E49E68C32D\",\n      \"CustomerLocation\": \"USA\",\n      \"IsReportedByAlternateContact\": false,\n      \"ResolutionEscLink_Category\": \"Frs_data_escalation_watch\",\n      \"ResolutionEscLink_RecID\": \"2E8A8CA68EF24570875FDE344CDB424D\",\n      \"ResolutionEscLink\": \"2E8A8CA68EF24570875FDE344CDB424D\",\n      \"ResponseEscLink_Category\": \"Frs_data_escalation_watch\",\n      \"ResponseEscLink_RecID\": \"992FA3CD128444CB9BB03CD05403A787\",\n      \"ResponseEscLink\": \"992FA3CD128444CB9BB03CD05403A787\",\n      \"WaitingEscLink_Category\": \"Frs_data_escalation_watch\",\n      \"WaitingEscLink_RecID\": \"59F8F198EAE245679042963F4B223157\",\n      \"WaitingEscLink\": \"59F8F198EAE245679042963F4B223157\",\n      \"ClosingEscLink_Category\": \"Frs_data_escalation_watch\",\n      \"ClosingEscLink_RecID\": \"B7F617606A9749CE9E213CA9C124F32D\",\n      \"ClosingEscLink\": \"B7F617606A9749CE9E213CA9C124F32D\",\n      \"AlternateContactEmail\": null,\n      \"OrganizationUnitID\": \"GMI\",\n      \"ReportingOrgUnitID_Valid\": \"4A05123D660F408997A4FEE714DAD111\",\n      \"ReportingOrgUnitID\": \"GMI\",\n      \"TypeOfIncident\": \"Failure\",\n      \"AlternateContactPhone\": null,\n      \"TeamManagerEmail\": \"change@example.com\",\n      \"ProblemLink_Category\": null,\n      \"ProblemLink_RecID\": null,\n      \"ProblemLink\": null,\n      \"CustomerDepartment\": \"Corporate IT\",\n      \"ActualService_Valid\": \"A912E98E55844765934A787FF3586F34\",\n      \"ActualService\": \"Service Desk\",\n      \"CostPerMinute_Currency\": \"USD\",\n      \"CostPerMinute_CurrencyValid\": null,\n      \"CostPerMinute\": \"0.4000\",\n      \"IsInFinalState\": false,\n      \"IsReclassifiedForResolution\": false,\n      \"KnowledgeLink_Category\": null,\n      \"KnowledgeLink_RecID\": null,\n      \"KnowledgeLink\": null,\n      \"PreviousState\": null,\n      \"ResolvedByIncidentNumber\": null,\n      \"TotalTimeSpent\": null,\n      \"RespondedBy\": null,\n      \"RespondedDateTime\": null,\n      \"OrgUnitLink_Category\": \"OrganizationalUnit\",\n      \"OrgUnitLink_RecID\": \"4A05123D660F408997A4FEE714DAD111\",\n      \"OrgUnitLink\": \"4A05123D660F408997A4FEE714DAD111\",\n      \"OwningOrgUnitId_Valid\": \"4A05123D660F408997A4FEE714DAD111\",\n      \"OwningOrgUnitId\": \"GMI\",\n      \"ProgressBarPosition\": \"3\",\n      \"ResolvedByType\": null,\n      \"ReportedBy\": null,\n      \"NewNotes\": null,\n      \"CreatedByType\": \"Web Client\",\n      \"SLADisplayText\": \"\",\n      \"ServiceReqLink_Category\": null,\n      \"ServiceReqLink_RecID\": null,\n      \"ServiceReqLink\": null,\n      \"ReadOnly\": false,\n      \"Cost_Currency\": \"USD\",\n      \"Cost_CurrencyValid\": null,\n      \"Cost\": \"0.0000\",\n      \"IncidentDetailWorkflowTag\": null,\n      \"IncidentDetailSummary\": null,\n      \"IsApprovalNeeded\": false,\n      \"Approver_Valid\": \"D712FED92D154257AB053F8BF4D24015\",\n      \"Approver\": \"DemoHR.user@ivanticlouddev.com\",\n      \"IsDSMTaskExisted\": false,\n      \"ApprovalStatus\": null,\n      \"SocialTextHeader\": \"Incident 12211: 2nd test from postman\",\n      \"Subcategory_Valid\": null,\n      \"Subcategory\": null,\n      \"helpdesk_Priority_Valid\": null,\n      \"helpdesk_Priority\": null,\n      \"ViewType\": null,\n      \"IncidentNetworkUserName\": \"Admin\",\n      \"SendSurveyNotification\": false,\n      \"EntityLink_Category\": \"OrganizationalUnit\",\n      \"EntityLink_RecID\": \"4A05123D660F408997A4FEE714DAD111\",\n      \"EntityLink\": \"4A05123D660F408997A4FEE714DAD111\",\n      \"EventCIRecId\": null,\n      \"IsMasterIncident\": false,\n      \"IsResolvedByMaster\": false,\n      \"MasterIncidentLink_Category\": null,\n      \"MasterIncidentLink_RecID\": null,\n      \"MasterIncidentLink\": null,\n      \"ServiceOwnerEmail\": \"admin@saasitdemo.com\",\n      \"IsRelatedIncidentUpdate\": false,\n      \"IsRelatedIncidentResolutionUpdate\": false,\n      \"IsUnRead\": false,\n      \"HRCaseLink_Category\": null,\n      \"HRCaseLink_RecID\": null,\n      \"HRCaseLink\": null,\n      \"ivnt_RequestforInformationorData\": false,\n      \"ivnt_UpdateRFI\": \"Chat Incident(s)\",\n      \"AddChatconversationtoActivityHistory\": false,\n      \"ivnt_TeamsUserDetailsLink_Category\": null,\n      \"ivnt_TeamsUserDetailsLink_RecID\": null,\n      \"ivnt_TeamsUserDetailsLink\": null,\n      \"VirimaAssetID\": null,\n      \"RecommendedCategory\": null,\n      \"RecommendedService\": null,\n      \"RecommendedSubCategory\": null,\n      \"Accuracy\": null,\n      \"IsRecommended\": false,\n      \"RecomService\": null,\n      \"RecomCategory\": null,\n      \"RecomSubCategory\": null,\n      \"IsRunTicketClassification\": true\n    },\n    {\n      \"ActualCategory_Valid\": \"601387668EAE4F09BB6D8DE4E922B2C7\",\n      \"ActualCategory\": \"Connectivity\",\n      \"Category_Valid\": \"601387668EAE4F09BB6D8DE4E922B2C7\",\n      \"Category\": \"Connectivity\",\n      \"CauseCode_Valid\": null,\n      \"CauseCode\": null,\n      \"ClosedBy\": null,\n      \"ClosedDateTime\": null,\n      \"ClosedDuration\": null,\n      \"CreatedBy\": \"jeffrey.fleishman\",\n      \"CreatedDateTime\": \"2022-12-23T05:09:12Z\",\n      \"Email\": \"admin@saasitdemo.com\",\n      \"FirstCallResolution\": false,\n      \"Impact_Valid\": null,\n      \"Impact\": null,\n      \"IncidentNumber\": 12210,\n      \"IsNotification\": true,\n      \"IsVIP\": false,\n      \"IsWorkAround\": false,\n      \"LastModBy\": \"InternalServices\",\n      \"LastModDateTime\": \"2022-12-23T05:09:17Z\",\n      \"Phone\": \"7195551254\",\n      \"Priority_Valid\": \"29CD5D78E16F4D82916C3E933A600096\",\n      \"Priority\": \"3\",\n      \"ProfileFullName\": \"Administrator Admin\",\n      \"ProfileLink_Category\": \"Employee\",\n      \"ProfileLink_RecID\": \"FB884D18F7B746A0992880F2DFFE749C\",\n      \"ProfileLink\": \"FB884D18F7B746A0992880F2DFFE749C\",\n      \"RecId\": \"64B80DD3EADB4B419A9AB22A2B7FED5A\",\n      \"Resolution\": null,\n      \"Service_Valid\": \"A912E98E55844765934A787FF3586F34\",\n      \"Service\": \"Service Desk\",\n      \"SLA\": \"\",\n      \"SLALink_Category\": null,\n      \"SLALink_RecID\": null,\n      \"SLALink\": null,\n      \"Source_Valid\": \"EF789CE160E742F99623DBB4D29C045C\",\n      \"Source\": \"Phone\",\n      \"Status_Valid\": \"AB3D0090B6D8471FB0D2720D301A22AF\",\n      \"Status\": \"Logged\",\n      \"Subject\": \"test from postman\",\n      \"Symptom\": \"test\",\n      \"Urgency_Valid\": null,\n      \"Urgency\": null,\n      \"LoginId\": \"Admin\",\n      \"Owner_Valid\": \"BFD1FA77D32F41E8AA5A54E68D58B589\",\n      \"Owner\": \"jeffrey.fleishman\",\n      \"OwnerTeam_Valid\": \"2E4BABD54FB9420D94F836F0D9B80C47\",\n      \"OwnerTeam\": \"Service Desk\",\n      \"OwnerType\": \"Employee\",\n      \"IsNewRecord\": false,\n      \"AlternateContactLink_Category\": null,\n      \"AlternateContactLink_RecID\": null,\n      \"AlternateContactLink\": null,\n      \"ResolvedDateTime\": null,\n      \"ResolvedBy\": null,\n      \"HoursOfOperation_Valid\": \"FF57246B2E0047D193C1AEC1011D746B\",\n      \"HoursOfOperation\": \"Weekly HOP\",\n      \"OwnerEmail\": \"jfleishman@connectall.com\",\n      \"OwnerTeamEmail\": \"change@example.com\",\n      \"OwnershipAssignmentEmail\": \"change@example.com\",\n      \"CustomerLocation_Valid\": \"45199627E18542038C2818E49E68C32D\",\n      \"CustomerLocation\": \"USA\",\n      \"IsReportedByAlternateContact\": false,\n      \"ResolutionEscLink_Category\": \"Frs_data_escalation_watch\",\n      \"ResolutionEscLink_RecID\": \"76262C7ECC314DA9A966E758BC9E9376\",\n      \"ResolutionEscLink\": \"76262C7ECC314DA9A966E758BC9E9376\",\n      \"ResponseEscLink_Category\": \"Frs_data_escalation_watch\",\n      \"ResponseEscLink_RecID\": \"88F4C6FA6FAE49579A24D9829DF5F8B0\",\n      \"ResponseEscLink\": \"88F4C6FA6FAE49579A24D9829DF5F8B0\",\n      \"WaitingEscLink_Category\": \"Frs_data_escalation_watch\",\n      \"WaitingEscLink_RecID\": \"9A19EDE3BE564380966D3713E2817E13\",\n      \"WaitingEscLink\": \"9A19EDE3BE564380966D3713E2817E13\",\n      \"ClosingEscLink_Category\": \"Frs_data_escalation_watch\",\n      \"ClosingEscLink_RecID\": \"0885749A2FEB438B9B1CBDC94F3FF5CB\",\n      \"ClosingEscLink\": \"0885749A2FEB438B9B1CBDC94F3FF5CB\",\n      \"AlternateContactEmail\": null,\n      \"OrganizationUnitID\": \"GMI\",\n      \"ReportingOrgUnitID_Valid\": \"4A05123D660F408997A4FEE714DAD111\",\n      \"ReportingOrgUnitID\": \"GMI\",\n      \"TypeOfIncident\": \"Failure\",\n      \"AlternateContactPhone\": null,\n      \"TeamManagerEmail\": \"change@example.com\",\n      \"ProblemLink_Category\": null,\n      \"ProblemLink_RecID\": null,\n      \"ProblemLink\": null,\n      \"CustomerDepartment\": \"Corporate IT\",\n      \"ActualService_Valid\": \"A912E98E55844765934A787FF3586F34\",\n      \"ActualService\": \"Service Desk\",\n      \"CostPerMinute_Currency\": \"USD\",\n      \"CostPerMinute_CurrencyValid\": null,\n      \"CostPerMinute\": \"0.4000\",\n      \"IsInFinalState\": false,\n      \"IsReclassifiedForResolution\": false,\n      \"KnowledgeLink_Category\": null,\n      \"KnowledgeLink_RecID\": null,\n      \"KnowledgeLink\": null,\n      \"PreviousState\": null,\n      \"ResolvedByIncidentNumber\": null,\n      \"TotalTimeSpent\": null,\n      \"RespondedBy\": null,\n      \"RespondedDateTime\": null,\n      \"OrgUnitLink_Category\": \"OrganizationalUnit\",\n      \"OrgUnitLink_RecID\": \"4A05123D660F408997A4FEE714DAD111\",\n      \"OrgUnitLink\": \"4A05123D660F408997A4FEE714DAD111\",\n      \"OwningOrgUnitId_Valid\": \"978ABB09369944C1991468FC458F488E\",\n      \"OwningOrgUnitId\": \"Default\",\n      \"ProgressBarPosition\": \"1\",\n      \"ResolvedByType\": null,\n      \"ReportedBy\": null,\n      \"NewNotes\": null,\n      \"CreatedByType\": \"Web Client\",\n      \"SLADisplayText\": \"\",\n      \"ServiceReqLink_Category\": null,\n      \"ServiceReqLink_RecID\": null,\n      \"ServiceReqLink\": null,\n      \"ReadOnly\": false,\n      \"Cost_Currency\": \"USD\",\n      \"Cost_CurrencyValid\": null,\n      \"Cost\": \"0.0000\",\n      \"IncidentDetailWorkflowTag\": null,\n      \"IncidentDetailSummary\": null,\n      \"IsApprovalNeeded\": false,\n      \"Approver_Valid\": \"D712FED92D154257AB053F8BF4D24015\",\n      \"Approver\": \"DemoHR.user@ivanticlouddev.com\",\n      \"IsDSMTaskExisted\": false,\n      \"ApprovalStatus\": null,\n      \"SocialTextHeader\": \"Incident 12210: test from postman\",\n      \"Subcategory_Valid\": null,\n      \"Subcategory\": null,\n      \"helpdesk_Priority_Valid\": null,\n      \"helpdesk_Priority\": null,\n      \"ViewType\": null,\n      \"IncidentNetworkUserName\": \"Admin\",\n      \"SendSurveyNotification\": true,\n      \"EntityLink_Category\": \"OrganizationalUnit\",\n      \"EntityLink_RecID\": \"4A05123D660F408997A4FEE714DAD111\",\n      \"EntityLink\": \"4A05123D660F408997A4FEE714DAD111\",\n      \"EventCIRecId\": null,\n      \"IsMasterIncident\": false,\n      \"IsResolvedByMaster\": false,\n      \"MasterIncidentLink_Category\": null,\n      \"MasterIncidentLink_RecID\": null,\n      \"MasterIncidentLink\": null,\n      \"ServiceOwnerEmail\": \"admin@saasitdemo.com\",\n      \"IsRelatedIncidentUpdate\": false,\n      \"IsRelatedIncidentResolutionUpdate\": false,\n      \"IsUnRead\": false,\n      \"HRCaseLink_Category\": null,\n      \"HRCaseLink_RecID\": null,\n      \"HRCaseLink\": null,\n      \"ivnt_RequestforInformationorData\": false,\n      \"ivnt_UpdateRFI\": \"Chat Incident(s)\",\n      \"AddChatconversationtoActivityHistory\": false,\n      \"ivnt_TeamsUserDetailsLink_Category\": null,\n      \"ivnt_TeamsUserDetailsLink_RecID\": null,\n      \"ivnt_TeamsUserDetailsLink\": null,\n      \"VirimaAssetID\": null,\n      \"RecommendedCategory\": null,\n      \"RecommendedService\": null,\n      \"RecommendedSubCategory\": null,\n      \"Accuracy\": null,\n      \"IsRecommended\": false,\n      \"RecomService\": null,\n      \"RecomCategory\": null,\n      \"RecomSubCategory\": null,\n      \"IsRunTicketClassification\": true\n    }\n  ]\n}","contentAvailable":true,"statusCode":2},"Request":{"specId":634,"type":"Request","adapterType":null,"specType":null,"status":"Active","specification":null,"samplePayload":null,"contentAvailable":false,"statusCode":2}}}},"default":true}]